mytestpackage435/__init__.py
mytestpackage435-0.1.0.dist-info/METADATA
mytestpackage435-0.1.0.dist-info/WHEEL
mytestpackage435-0.1.0.dist-info/RECORD
