Metadata-Version: 2.4
Name: mytestpackage435
Version: 0.1.0
Summary: my awesome test package
License: MIT
Author: Boopathy
Author-email: boopathy.krishnasamy.ext@siemens-energy.com
Requires-Python: >=3.11
Classifier: License :: OSI Approved :: MIT License
Classifier: Programming Language :: Python :: 3
Classifier: Programming Language :: Python :: 3.11
Classifier: Programming Language :: Python :: 3.12
Classifier: Programming Language :: Python :: 3.13
Classifier: Programming Language :: Python :: 3.14
Requires-Dist: requests (>=2.32.5,<3.0.0)
